marker_alignments/__init__.py
marker_alignments/main.py
marker_alignments/mcl.py
marker_alignments/pysam2.py
marker_alignments/refdb_pattern.py
marker_alignments/store.py
marker_alignments/write.py
marker_alignments-0.4.2.dist-info/LICENSE
marker_alignments-0.4.2.dist-info/METADATA
marker_alignments-0.4.2.dist-info/WHEEL
marker_alignments-0.4.2.dist-info/entry_points.txt
marker_alignments-0.4.2.dist-info/top_level.txt
marker_alignments-0.4.2.dist-info/RECORD
