Metadata-Version: 2.1
Name: marker-alignments
Version: 0.4.2
Summary: Process and summarise alignments of metagenomic sequencing reads to reference databases of marker genes
Home-page: http://github.com/wbazant/marker_alignments
Author: wbazant
Author-email: wojciech.bazant@gmail.com
License: MIT
Requires-Python: >=3.6
License-File: LICENSE
Requires-Dist: pysam
Requires-Dist: scipy
Requires-Dist: numpy
Requires-Dist: scikit-learn
